[{"keyword":"Feature","type":"feature","description":"","line":2,"name":"cotizacion de seguros banorte","uri":"C:\\Users\\frank\\OneDrive - Instituto Politecnico Nacional\\Documents\\playwright-automation\\seguros\\features\\secure.feature","tags":[{"location":{"line":1,"column":1},"name":"@quoter","id":"e881e981-d014-4781-9d1c-cfdae353514b"}],"elements":[{"keyword":"Scenario","type":"scenario","description":"","name":"cotizacion de seguro de auto","tags":[{"name":"@quoter","astNodeId":"e881e981-d014-4781-9d1c-cfdae353514b"}],"id":"cotizacion-de-seguros-banortecotizacion-de-seguro-de-auto","steps":[{"arguments":[],"keyword":"Before","name":"","result":{"status":"passed","duration":13000000},"line":null,"match":{"location":"can not be determined with webdriver.io"}},{"arguments":[],"keyword":"Given","name":"I am on the banorte quoter home page","result":{"status":"passed","duration":6549000000},"line":null,"match":{"location":"can not be determined with webdriver.io"}},{"arguments":[],"keyword":"When","name":"I select my car type","result":{"status":"passed","duration":4502000000},"line":null,"match":{"location":"can not be determined with webdriver.io"}},{"arguments":[],"keyword":"And","name":"I select my car year","result":{"status":"passed","duration":1795000000},"line":null,"match":{"location":"can not be determined with webdriver.io"}},{"arguments":[],"keyword":"And","name":"I select my car brand","result":{"status":"passed","duration":9463000000},"line":null,"match":{"location":"can not be determined with webdriver.io"}},{"arguments":[],"keyword":"And","name":"I select my car version","result":{"status":"passed","duration":6221000000},"line":null,"match":{"location":"can not be determined with webdriver.io"}},{"arguments":[],"keyword":"And","name":"I introduce my cp code for continue with the second phase","result":{"status":"passed","duration":6345000000},"line":null,"match":{"location":"can not be determined with webdriver.io"}},{"arguments":[],"keyword":"Then","name":"I can see the personal data form","result":{"status":"passed","duration":128000000},"line":null,"match":{"location":"can not be determined with webdriver.io"}},{"arguments":[],"keyword":"When","name":"I fill the personal data form","result":{"status":"passed","duration":20058000000},"line":null,"match":{"location":"can not be determined with webdriver.io"}},{"arguments":[],"keyword":"Then","name":"I can see the quoter results","result":{"status":"passed","duration":63000000},"line":null,"match":{"location":"can not be determined with webdriver.io"}},{"arguments":[],"keyword":"When","name":"I view my car info and extract it","result":{"status":"passed","duration":16619000000},"line":null,"match":{"location":"can not be determined with webdriver.io"}},{"arguments":[],"keyword":"After","name":"","result":{"status":"passed","duration":8000000},"line":null,"match":{"location":"can not be determined with webdriver.io"}}]}],"id":"cotizacion-de-seguros-banorte","metadata":{"browser":{"name":"chrome","version":"131.0.6778.85"},"device":"Device name not known","platform":{"name":"windows","version":"Version not known"}}}]
