[{"keyword":"Feature","type":"feature","description":"","line":2,"name":"cotizacion de seguros banorte","uri":"C:\\Users\\frank\\OneDrive - Instituto Politecnico Nacional\\Documents\\playwright-automation\\seguros\\features\\secure.feature","tags":[{"location":{"line":1,"column":1},"name":"@quoter","id":"62f1b2e1-ea69-48e9-915f-c7d7a3fe1c87"}],"elements":[{"keyword":"Scenario","type":"scenario","description":"","name":"cotizacion de seguro de auto","tags":[{"name":"@quoter","astNodeId":"62f1b2e1-ea69-48e9-915f-c7d7a3fe1c87"}],"id":"cotizacion-de-seguros-banortecotizacion-de-seguro-de-auto","steps":[{"arguments":[],"keyword":"Before","name":"","result":{"status":"passed","duration":45000000},"line":null,"match":{"location":"can not be determined with webdriver.io"}},{"arguments":[],"keyword":"Given","name":"I am on the banorte quoter home page","result":{"status":"passed","duration":6210000000},"line":null,"match":{"location":"can not be determined with webdriver.io"}},{"arguments":[],"keyword":"When","name":"I select my car type","result":{"status":"passed","duration":2247000000},"line":null,"match":{"location":"can not be determined with webdriver.io"}},{"arguments":[],"keyword":"And","name":"I select my car year","result":{"status":"passed","duration":1435000000},"line":null,"match":{"location":"can not be determined with webdriver.io"}},{"arguments":[],"keyword":"And","name":"I select my car brand","result":{"status":"passed","duration":2271000000},"line":null,"match":{"location":"can not be determined with webdriver.io"}},{"arguments":[],"keyword":"After","name":"","result":{"status":"passed","duration":6000000},"line":null,"match":{"location":"can not be determined with webdriver.io"}}]}],"id":"cotizacion-de-seguros-banorte","metadata":{"browser":{"name":"chrome","version":"131.0.6778.85"},"device":"Device name not known","platform":{"name":"windows","version":"Version not known"}}}]
